{
  "id": "antoine-daniel",
  "name": "St. Antoine Daniel",
  "birthYear": 1601,
  "deathYear": 1648,
  "feastDay": "September 26",
  "primaryTradition": "Latin",
  "roles": [
    "priest",
    "missionary",
    "martyr"
  ],
  "orthodoxyStatus": "canonized",
  "isMartyr": true,
  "locations": [
    {
      "placeId": "canada",
      "description": "Jesuit missionary, one of the North American Martyrs in Canada"
    }
  ],
  "wikipediaUrl": "https://en.wikipedia.org/wiki/Antoine_Daniel",
  "imageUrl": "https://upload.wikimedia.org/wikipedia/commons/thumb/d/d9/Faubourg_St._Antoine._G.17458.jpg/330px-Faubourg_St._Antoine._G.17458.jpg",
  "summary": "Antoine Daniel was a French Jesuit priest and martyr who worked as a missionary among the Huron people in New France (Canada). He was a skilled teacher and established a school for Huron children. When the Iroquois attacked the mission at Teanaostaye, he was killed while celebrating Mass. He is one of the North American Martyrs and is remembered for his educational work and his dedication to the Huron people.",
  "keyQuotes": []
}

