{
  "id": "margaret-cortona",
  "name": "St. Margaret of Cortona",
  "birthYear": 1247,
  "deathYear": 1297,
  "feastDay": "February 22",
  "primaryTradition": "Latin",
  "roles": [
    "tertiary",
    "penitent"
  ],
  "orthodoxyStatus": "canonized",
  "isMartyr": false,
  "locations": [
    {
      "placeId": "cortona",
      "description": "Franciscan tertiary"
    }
  ],
  "wikipediaUrl": "https://en.wikipedia.org/wiki/Margaret_of_Cortona",
  "imageUrl": "https://upload.wikimedia.org/wikipedia/commons/thumb/d/d2/Giovanni_Lanfranco_-_Ecstasy_of_St_Margaret_of_Cortona_-_WGA12453.jpg/330px-Giovanni_Lanfranco_-_Ecstasy_of_St_Margaret_of_Cortona_-_WGA12453.jpg",
  "summary": "Margaret of Cortona was an Italian penitent who became a Franciscan tertiary. After living in sin and bearing an illegitimate child, she experienced a conversion and devoted herself to penance and works of charity. She founded a hospital for the poor and became known for her visions, ecstasies, and devotion to the Eucharist. She is known as the patron saint of the homeless, single mothers, and those who have lost children.",
  "keyQuotes": [],
  "writings": [],
  "newAdventUrl": "https://www.newadvent.org/cathen/09653b.htm"
}